{
  "active": false,
  "connections": {
    "If1": {
      "main": [
        [],
        [
          {
            "node": "Wait2",
            "type": "main",
            "index": 0
          }
        ]
      ]
    },
    "Wait2": {
      "main": [
        [
          {
            "node": "Obtener vídeo",
            "type": "main",
            "index": 0
          }
        ]
      ]
    },
    "When clicking ‘Test workflow’": {
      "main": [
        [
          {
            "node": "Edit Fields",
            "type": "main",
            "index": 0
          }
        ]
      ]
    },
    "Generador de video": {
      "main": [
        [
          {
            "node": "Wait",
            "type": "main",
            "index": 0
          }
        ]
      ]
    },
    "Obtener vídeo": {
      "main": [
        [
          {
            "node": "If1",
            "type": "main",
            "index": 0
          }
        ]
      ]
    },
    "Edit Fields": {
      "main": [
        [
          {
            "node": "Limpiamos el texto",
            "type": "main",
            "index": 0
          }
        ]
      ]
    },
    "Limpiamos el texto": {
      "main": [
        [
          {
            "node": "Generador de video",
            "type": "main",
            "index": 0
          }
        ]
      ]
    },
    "Wait": {
      "main": [
        [
          {
            "node": "Obtener vídeo",
            "type": "main",
            "index": 0
          }
        ]
      ]
    }
  },
  "createdAt": "2025-10-17T10:50:35.191Z",
  "id": "IQewawWb3WblMtSG",
  "isArchived": false,
  "meta": null,
  "name": "My workflow 12",
  "nodes": [
    {
      "parameters": {
        "conditions": {
          "options": {
            "caseSensitive": true,
            "leftValue": "",
            "typeValidation": "strict",
            "version": 2
          },
          "conditions": [
            {
              "id": "dd44e8b9-64ae-4a91-8d19-966910447f71",
              "leftValue": "={{ $json.data.status }}",
              "rightValue": "completed",
              "operator": {
                "type": "string",
                "operation": "equals",
                "name": "filter.operator.equals"
              }
            }
          ],
          "combinator": "and"
        },
        "options": {}
      },
      "type": "n8n-nodes-base.if",
      "typeVersion": 2.2,
      "position": [
        1472,
        512
      ],
      "id": "c94d2483-3c2b-4020-8452-e7f05ba9c444",
      "name": "If1"
    },
    {
      "parameters": {
        "amount": 1,
        "unit": "minutes"
      },
      "type": "n8n-nodes-base.wait",
      "typeVersion": 1.1,
      "position": [
        1664,
        592
      ],
      "id": "6ec3a121-fb2a-42ba-abbd-6eb860617dc1",
      "name": "Wait2",
      "webhookId": "REDACTED"
    },
    {
      "parameters": {},
      "type": "n8n-nodes-base.manualTrigger",
      "typeVersion": 1,
      "position": [
        0,
        0
      ],
      "id": "00a2aee1-ca3b-4ee3-8643-7c9436644b66",
      "name": "When clicking ‘Test workflow’"
    },
    {
      "parameters": {
        "method": "POST",
        "url": "https://api.heygen.com/v2/video/generate",
        "authentication": "genericCredentialType",
        "genericAuthType": "httpHeaderAuth",
        "sendHeaders": true,
        "headerParameters": {
          "parameters": [
            {
              "name": "accept",
              "value": "application/json"
            }
          ]
        },
        "sendBody": true,
        "specifyBody": "json",
        "jsonBody": "={\n  \"video_inputs\": [\n    {\n      \"character\": {\n        \"type\": \"avatar\",\n        \"avatar_id\": \"b5f4a2086af947819447a76c268490da\",\n        \"avatar_style\": \"normal\"\n      },\n      \"voice\": {\n        \"type\": \"text\",\n        \"input_text\": \"{{ $json.cleaned }}\",\n        \"voice_id\": \"e9182da95a92499a8e93d51e97da5489\",\n        \"speed\": 1.1\n      }\n    }\n  ],\n  \"dimension\": {\n    \"width\": 360,\n    \"height\": 740\n  }\n}",
        "options": {}
      },
      "type": "n8n-nodes-base.httpRequest",
      "typeVersion": 4.2,
      "position": [
        432,
        512
      ],
      "id": "e0f4bbdd-51f0-4e9d-8737-b845036f5a5d",
      "name": "Generador de video",
      "credentials": {}
    },
    {
      "parameters": {
        "url": "https://api.heygen.com/v1/video_status.get",
        "authentication": "genericCredentialType",
        "genericAuthType": "httpHeaderAuth",
        "sendQuery": true,
        "queryParameters": {
          "parameters": [
            {
              "name": "video_id",
              "value": "={{ $('Generador de video').item.json.data.video_id }}"
            }
          ]
        },
        "sendHeaders": true,
        "headerParameters": {
          "parameters": [
            {
              "name": "accept",
              "value": "application/json"
            }
          ]
        },
        "options": {}
      },
      "type": "n8n-nodes-base.httpRequest",
      "typeVersion": 4.2,
      "position": [
        1168,
        512
      ],
      "id": "e106aa2d-78db-40a6-9e50-28b4511f0595",
      "name": "Obtener vídeo",
      "credentials": {}
    },
    {
      "parameters": {
        "assignments": {
          "assignments": [
            {
              "id": "191ad70f-ad8c-4864-8ff4-33b57b2a08dd",
              "name": "texto",
              "value": "Ahora puedes crear videos en cualquier idioma que quieras y llegar a todo el mundo.",
              "type": "string"
            }
          ]
        },
        "options": {}
      },
      "type": "n8n-nodes-base.set",
      "typeVersion": 3.4,
      "position": [
        208,
        0
      ],
      "id": "884e5545-20e6-45ab-a6f0-d5d0f379ebb1",
      "name": "Edit Fields"
    },
    {
      "parameters": {
        "jsCode": "return items.map(item => {\n  const originalText = $input.first().json.texto\n\n  if (typeof originalText !== 'string') {\n    return {\n      json: {\n        error: 'El campo \"text\" no existe o no es un texto',\n        original: originalText\n      }\n    };\n  }\n\n  let cleaned = originalText\n    .replace(/<[^>]*>/g, '')                 // Quitar HTML\n    .replace(/\\r?\\n|\\r/g, ' ')               // Saltos de línea a espacio\n    .replace(/\\t+/g, ' ')                    // Tabs a espacio\n    .replace(/[^\\p{L}\\p{N},¿?\\s]+/gu, '')    // Letras, números, comas, espacios, ¿, ?\n    .replace(/\\s+/g, ' ')                    // Normalizar múltiples espacios\n    .trim();                                 // Quitar espacios extremos\n\n  return {\n    json: {\n      cleaned\n    }\n  };\n});\n"
      },
      "type": "n8n-nodes-base.code",
      "typeVersion": 2,
      "position": [
        512,
        112
      ],
      "id": "af8403a5-1a5d-48a1-8746-a420e4995916",
      "name": "Limpiamos el texto"
    },
    {
      "parameters": {
        "amount": 1,
        "unit": "minutes"
      },
      "type": "n8n-nodes-base.wait",
      "typeVersion": 1.1,
      "position": [
        640,
        512
      ],
      "id": "68e4fccf-c3d9-4a34-9a48-648851b14265",
      "name": "Wait",
      "webhookId": "REDACTED"
    }
  ],
  "origin": "n8n",
  "pinData": {},
  "repo": {
    "owner": "abdeidr",
    "name": "n8n"
  },
  "settings": {
    "executionOrder": "v1"
  },
  "shared": [
    {
      "createdAt": "2025-10-17T10:50:35.198Z",
      "updatedAt": "2025-10-17T10:50:35.198Z",
      "role": "workflow:owner",
      "workflowId": "IQewawWb3WblMtSG",
      "projectId": "xdZYvePgLSibegaD"
    }
  ],
  "staticData": null,
  "tags": [],
  "triggerCount": 0,
  "updatedAt": "2025-10-18T20:18:03.000Z",
  "versionId": "828d847d-bb81-4d12-928f-b144ae1d2a08"
}